integralclient/__init__.py
integralclient/service_exception.py
integral_client-1.1.9.dist-info/COPYING
integral_client-1.1.9.dist-info/METADATA
integral_client-1.1.9.dist-info/WHEEL
integral_client-1.1.9.dist-info/entry_points.txt
integral_client-1.1.9.dist-info/top_level.txt
integral_client-1.1.9.dist-info/RECORD
